setup.py
mul/__init__.py
mul/table.py
mul_table.egg-info/PKG-INFO
mul_table.egg-info/SOURCES.txt
mul_table.egg-info/dependency_links.txt
mul_table.egg-info/top_level.txt